pyceps/__init__.py
pyceps/carto.py
pyceps/cli.py
pyceps/interpolation.py
pyceps/precision.py
pyceps/study.py
pyceps/utils.py
pyceps/datatypes/__init__.py
pyceps/datatypes/exceptions.py
pyceps/datatypes/lesions.py
pyceps/datatypes/signals.py
pyceps/datatypes/surface.py
pyceps/datatypes/carto/__init__.py
pyceps/datatypes/carto/cartotypes.py
pyceps/datatypes/carto/paso.py
pyceps/datatypes/carto/visitag.py
pyceps/datatypes/precision/__init__.py
pyceps/datatypes/precision/precisiontypes.py
pyceps/fileio/__init__.py
pyceps/fileio/cartoio.py
pyceps/fileio/igb.py
pyceps/fileio/pathtools.py
pyceps/fileio/precisionio.py
pyceps/fileio/writer.py
pyceps/fileio/xmlio.py
pyceps/visualize/__init__.py
pyceps/visualize/colormaps.json
pyceps/visualize/dashapp.py
pyceps/visualize/dashelements.py
pyceps/visualize/dashlayout.py
pyceps/visualize/dashutils.py
pyceps-1.1.2.dist-info/licenses/LICENSE.txt
pyceps-1.1.2.dist-info/METADATA
pyceps-1.1.2.dist-info/WHEEL
pyceps-1.1.2.dist-info/entry_points.txt
pyceps-1.1.2.dist-info/top_level.txt
pyceps-1.1.2.dist-info/RECORD
