Metadata-Version: 2.4
Name: pyCEPS
Version: 1.1.2
Summary: pyceps provides methods for importing EP studies from commercial Clinical Mapping Systems and to export data to openCARP compatible data formats.
Home-page: https://github.com/medunigraz/pyCEPS
Author: Robert Arnold
Author-email: robert.arnold@medunigraz.at
License: GPLv3+
Project-URL: Github, https://github.com/medunigraz/pyCEPS
Project-URL: Changelog, https://github.com/medunigraz/pyCEPS/blob/main/CHANGELOG.md
Classifier: License :: OSI Approved :: GNU General Public License v3 or later (GPLv3+)
Classifier: Programming Language :: Python
Classifier: Programming Language :: Python :: 3.8
Classifier: Programming Language :: Python :: 3.9
Classifier: Programming Language :: Python :: 3.10
Classifier: Programming Language :: Python :: 3.11
Classifier: Programming Language :: Python :: 3.12
Classifier: Development Status :: 4 - Beta
Classifier: Environment :: Console
Classifier: Intended Audience :: Science/Research
Requires-Python: >=3.8
License-File: LICENSE.txt
Requires-Dist: dash<3.0.0,>=2.15
Requires-Dist: numpy<1.26.0,>=1.19.5; python_version == "3.8"
Requires-Dist: numpy<2.0.0,>=1.22.4; python_version >= "3.9"
Requires-Dist: scipy==1.10.1; python_version == "3.8"
Requires-Dist: scipy>=1.12; python_version >= "3.9"
Requires-Dist: dash_bootstrap_components>=1.4.2
Requires-Dist: dash_vtk>=0.0.9
Requires-Dist: py7zr>=0.21.0
Requires-Dist: pandas==2.0.3; python_version == "3.8"
Requires-Dist: pandas==2.2.3; python_version >= "3.9"
Dynamic: author
Dynamic: author-email
Dynamic: classifier
Dynamic: description
Dynamic: description-content-type
Dynamic: home-page
Dynamic: license
Dynamic: license-file
Dynamic: project-url
Dynamic: requires-dist
Dynamic: requires-python
Dynamic: summary
